{"item": {"ID": "73202", "CountiesArea": "4060", "ZipCodePopulation": "27585", "HouseholdsPerZipcode": "9987.0000", "WhitePop": "21449", "BlackPop": "612", "HispanicPop": "7140", "AsianPop": "3296", "IndianPop": "365", "HawaiianPop": "116", "OtherPop": "3232", "MalePop": "13734", "FemalePop": "13851", "PersonsPerHousehold": "2.74", "AverageHouseValue": "456300.00", "IncomePerHousehold": "51461.00", "MedianAge": "40.70", "MedianAgeMale": "39.70", "MedianAgeFemale": "41.80", "AverageFamilySize": "3.25", "Bus03Establishments": "365", "Bus03Employment": "2324", "Bus03PayrollQuarter1": "15243", "Bus03PayrollAnnual": "69012", "Bus03EmploymentFlag": " ", "CBSAPop2003": null, "CBSADivPop2003": "9818605", "DeliveryActive": "10699", "DeliveryBusiness": "438", "DeliveryResidential": "10276", "DeliverySpecial": "10276", "DeliveryBox": "0", "DeliverySFDU": "7112", "DeliveryMFDU": "2717", "PopulationEstimate": "28156", "_109thDistrict": "0", "_109thArea": "0", "_110thDistrict": "28", "_110thArea": "218.45", "GrowthRank": "0", "GrowthHousingUnits2003": "0", "GrowthHousingUnits2004": "0", "GrowthIncreaseNumber": "0", "GrowthIncreasePercentage": "0.00", "Latitude": "34.280082", "Longitude": "-118.235202", "Elevation": "267.00", "AreaLand": "49.883000", "AreaWater": "0.060000", "Primary": "P", "State": "CA", "CityType": "P", "CityAliasType": null, "Classification": " ", "ZipCode": "91042", "CityAliasAbbr": null, "AreaCode": "818/747", "AreaCodeTemp": null, "AreaCodeTest": null, "City": "TUJUNGA", "CityAliasName": "TUJUNGA", "CountyName": "LOS ANGELES", "CountyFIPS": "037", "StateFIPS": "06", "CountyANSI": "037", "StateANSI": "06", "TimeZone": "8", "DayLightSaving": "Y", "MSA": "4472", "PMSA": "4480", "PMSAName": "Los Angeles-Long Beach, CA PMSA", "CSA": "348", "CSAName": "Los Angeles-Long Beach, CA", "CBSA": "31080", "CBSA_DIV": "31084", "CBSA_DIV_Name": "Los Angeles-Long Beach-Glendale, CA", "CBSA_Type": "Metro", "CBSA_Name": "Los Angeles-Long Beach-Anaheim, CA", "MSAName": "Los Angeles-Riverside-Orange County, CA", "Region": "West", "Division": "Pacific", "MailingName": "Y", "MultiCounty": " ", "Prev": "91041", "Next": "91043", "CityStateKey": "Z23623", "PreferredLastLineKey": "Z23623", "PreferredLastLineName": "TUJUNGA", "IntroDateZIP": "<2004-10", "IntroDateAlias": "<2004-10", "FacilityCode": "P", "CityDeliveryIndicator": "Y", "CarrierRouteRateSortation": "B", "FinanceNumber": "057944", "UniqueZIPName": null, "MixedCaseCity": "Tujunga", "MixedCaseAlias": "Tujunga", "SSA_State_County_Code": "05200", "Medicare_CBSA_Code": "31084", "Medicare_CBSA_Name": "Los Angeles-Long Beach-Glendale, CA", "Medicare_CBSA_Type": "Metro", "Medicare_Rating_Area_ID": "15"}}